{
  "module_id": "05-golden-image",
  "module_name": "Golden Image Creation",
  "status": "in_progress",
  "started_at": "2025-12-05T23:39:00Z",
  "operations": {
    "golden-image-create-vm": {
      "status": "completed",
      "started_at": "2025-12-05T23:30:00Z",
      "completed_at": "2025-12-05T23:31:00Z",
      "exit_code": 0
    },
    "golden-image-validate-vm": {
      "status": "completed",
      "started_at": "2025-12-05T23:31:00Z",
      "completed_at": "2025-12-05T23:32:00Z",
      "exit_code": 0
    },
    "golden-image-system-prep": {
      "status": "completed",
      "started_at": "2025-12-05T23:32:00Z",
      "completed_at": "2025-12-05T23:33:00Z",
      "exit_code": 0
    }
  }
}
